antibacterial_model/__init__.py
antibacterial_model/model.py
antibacterial_model/data/anti-bact-data.csv
antibacterial_model/data/anti-bact-model.pkl
antibacterial_model-1.0.8.dist-info/METADATA
antibacterial_model-1.0.8.dist-info/WHEEL
antibacterial_model-1.0.8.dist-info/top_level.txt
antibacterial_model-1.0.8.dist-info/RECORD
