Metadata-Version: 2.1
Name: antibacterial-model
Version: 1.0.8
Summary: A model for predicting antibacterial activity from SMILES strings
Author: Chonthicha Arbsuwan, Jiratchaya Nakbang
Author-email: chon7599@gmail.com, jiratchaya2356@gmail.com
Classifier: Development Status :: 3 - Alpha
Classifier: Intended Audience :: Developers
Classifier: License :: OSI Approved :: MIT License
Classifier: Programming Language :: Python :: 3
Classifier: Programming Language :: Python :: 3.6
Classifier: Programming Language :: Python :: 3.7
Classifier: Programming Language :: Python :: 3.8
Classifier: Programming Language :: Python :: 3.9
Requires-Python: >=3.6
Requires-Dist: numpy (==1.24.1)
Requires-Dist: rdkit (==2023.3.3)
Requires-Dist: scikit-learn (==1.2.1)
Requires-Dist: joblib (==1.2.0)
Requires-Dist: pandas (==1.5.3)
